satnogs_network_api_client-1.123.dist-info/licenses/LICENSE
satnogsnetworkapiclient/__init__.py
satnogsnetworkapiclient/_version.py
satnogsnetworkapiclient/api_client.py
satnogsnetworkapiclient/configuration.py
satnogsnetworkapiclient/exceptions.py
satnogsnetworkapiclient/model_utils.py
satnogsnetworkapiclient/rest.py
satnogsnetworkapiclient/api/__init__.py
satnogsnetworkapiclient/api/configuration_api.py
satnogsnetworkapiclient/api/jobs_api.py
satnogsnetworkapiclient/api/observations_api.py
satnogsnetworkapiclient/api/station_registration_api.py
satnogsnetworkapiclient/api/stations_api.py
satnogsnetworkapiclient/api/transmitters_api.py
satnogsnetworkapiclient/apis/__init__.py
satnogsnetworkapiclient/model/__init__.py
satnogsnetworkapiclient/model/demod_data.py
satnogsnetworkapiclient/model/inline_object.py
satnogsnetworkapiclient/model/inline_object1.py
satnogsnetworkapiclient/model/inline_response200.py
satnogsnetworkapiclient/model/inline_response400.py
satnogsnetworkapiclient/model/job.py
satnogsnetworkapiclient/model/new_observation.py
satnogsnetworkapiclient/model/observation.py
satnogsnetworkapiclient/model/paginated_observation_list.py
satnogsnetworkapiclient/model/patched_observation.py
satnogsnetworkapiclient/model/station.py
satnogsnetworkapiclient/model/station_antenna.py
satnogsnetworkapiclient/model/station_configuration.py
satnogsnetworkapiclient/model/status_enum.py
satnogsnetworkapiclient/model/transmitter.py
satnogsnetworkapiclient/model/transmitter_stats.py
satnogsnetworkapiclient/model/transmitter_status_enum.py
satnogsnetworkapiclient/model/transmitter_type_enum.py
satnogsnetworkapiclient/model/update_observation.py
satnogsnetworkapiclient/model/waterfall_status_enum.py
satnogsnetworkapiclient/models/__init__.py
satnogsnetworkapiclient/test/__init__.py
satnogsnetworkapiclient/test/test_configuration_api.py
satnogsnetworkapiclient/test/test_demod_data.py
satnogsnetworkapiclient/test/test_inline_object.py
satnogsnetworkapiclient/test/test_inline_object1.py
satnogs_network_api_client-1.123.dist-info/METADATA
satnogs_network_api_client-1.123.dist-info/WHEEL
satnogs_network_api_client-1.123.dist-info/top_level.txt
satnogs_network_api_client-1.123.dist-info/RECORD
